stadata/.DS_Store
stadata/__init__.py
stadata/main.py
stadata/material.py
stadata/semver_demo.py
stadata_semver-1.1.0.dist-info/METADATA
stadata_semver-1.1.0.dist-info/WHEEL
stadata_semver-1.1.0.dist-info/RECORD
